wander_game/__init__.py
wander_game-0.2.1.dist-info/METADATA
wander_game-0.2.1.dist-info/WHEEL
wander_game-0.2.1.dist-info/RECORD
