Metadata-Version: 2.1
Name: wander-game
Version: 0.2.1
Summary: simulate a trading Order Book
Author: leon_richard_tan
Requires-Python: >=3.10,<4.0
Classifier: Programming Language :: Python :: 3
Classifier: Programming Language :: Python :: 3.10
Classifier: Programming Language :: Python :: 3.11
Classifier: Programming Language :: Python :: 3.12
Classifier: Programming Language :: Python :: 3.13
Requires-Dist: numpy (>=2.1.2,<3.0.0)
